CMakeLists.txt
LICENSE
MANIFEST.in
Parfile
README.md
setup.py
include/bounding_box.h
include/clipper.h
include/converter.h
include/converter_types.h
include/converter_utils.h
include/data_reader.h
include/file_utils.h
include/graph.h
include/graph_utils.h
include/intersector.h
include/local_topology_analyzer.h
include/parameters_reader.h
include/parameters_utils.h
include/svgbuilder.h
include/tester.h
include/topology_analyzer.h
map2model_loop3d.egg-info/PKG-INFO
map2model_loop3d.egg-info/SOURCES.txt
map2model_loop3d.egg-info/dependency_links.txt
map2model_loop3d.egg-info/not-zip-safe
map2model_loop3d.egg-info/top_level.txt
pybind11/.appveyor.yml
pybind11/.gitmodules
pybind11/.readthedocs.yml
pybind11/.travis.yml
pybind11/CMakeLists.txt
pybind11/CONTRIBUTING.md
pybind11/ISSUE_TEMPLATE.md
pybind11/MANIFEST.in
pybind11/README.md
pybind11/setup.py
pybind11/docs/Makefile
pybind11/docs/basics.rst
pybind11/docs/benchmark.py
pybind11/docs/benchmark.rst
pybind11/docs/changelog.rst
pybind11/docs/classes.rst
pybind11/docs/compiling.rst
pybind11/docs/conf.py
pybind11/docs/faq.rst
pybind11/docs/index.rst
pybind11/docs/intro.rst
pybind11/docs/limitations.rst
pybind11/docs/pybind11-logo.png
pybind11/docs/pybind11_vs_boost_python1.png
pybind11/docs/pybind11_vs_boost_python1.svg
pybind11/docs/pybind11_vs_boost_python2.png
pybind11/docs/pybind11_vs_boost_python2.svg
pybind11/docs/reference.rst
pybind11/docs/release.rst
pybind11/docs/requirements.txt
pybind11/docs/upgrade.rst
pybind11/docs/_static/theme_overrides.css
pybind11/docs/advanced/classes.rst
pybind11/docs/advanced/embedding.rst
pybind11/docs/advanced/exceptions.rst
pybind11/docs/advanced/functions.rst
pybind11/docs/advanced/misc.rst
pybind11/docs/advanced/smart_ptrs.rst
pybind11/docs/advanced/cast/chrono.rst
pybind11/docs/advanced/cast/custom.rst
pybind11/docs/advanced/cast/eigen.rst
pybind11/docs/advanced/cast/functional.rst
pybind11/docs/advanced/cast/index.rst
pybind11/docs/advanced/cast/overview.rst
pybind11/docs/advanced/cast/stl.rst
pybind11/docs/advanced/cast/strings.rst
pybind11/docs/advanced/pycpp/index.rst
pybind11/docs/advanced/pycpp/numpy.rst
pybind11/docs/advanced/pycpp/object.rst
