Metadata-Version: 2.1
Name: map2model-loop3d
Version: 1.0.0
Summary: Perform topological analysis on 2D map data.
Home-page: https://github.com/Loop3D/map2model_cpp
Author: Yohan de Rose
Author-email: contact@loop3d.org
License: UNKNOWN
Platform: UNKNOWN
Classifier: Programming Language :: Python :: 3
Classifier: License :: OSI Approved :: MIT License
Classifier: Operating System :: OS Independent
Requires-Python: >=3.6
